{
	"en": {
		"language_name": "English",
		"menu.new_game": "New Game",
		"menu.load_game": "Load Game",
		"menu.options": "Options",
		"menu.quit": "Quit",
		"menu.back": "Back",
		"menu.resume": "Resume",
		"menu.save": "Save",
		"menu.load": "Load",
		"menu.title": "Title",
		"options.title": "Options",
		"options.resolution": "Resolution",
		"options.language": "Language",
		"options.controls": "Controls",
		"options.controls_mapping": "Keyboard / Controller Mapping",
		"options.ui_only": "UI only - settings are not applied yet.",
		"options.changed": "Option selected. Applying settings is not implemented yet.",
		"slot.new_game": "New Game",
		"slot.start_new_game": "Start New Game",
		"slot.load_game": "Load Game",
		"slot.save": "Save",
		"slot.load": "Load",
		"slot.confirm_overwrite": "Confirm Overwrite",
		"slot.overwrite_prompt": "Press again to overwrite Slot %d.",
		"slot.overwrite_warning": "This will overwrite existing save data.",
		"slot.empty": "Slot %d - Empty",
		"slot.summary": "Slot %d - %s  %s",
		"slot.unknown": "Unknown",
		"slot.no_time": "No time",
		"status.no_save_data": "No save data",
		"status.saved_slot": "Saved Slot %d",
		"status.loaded_slot": "Loaded Slot %d",
		"status.save_failed": "Save failed"
	},
	"ja": {
		"language_name": "日本語",
		"menu.new_game": "ニューゲーム",
		"menu.load_game": "ロード",
		"menu.options": "オプション",
		"menu.quit": "終了",
		"menu.back": "戻る",
		"menu.resume": "再開",
		"menu.save": "セーブ",
		"menu.load": "ロード",
		"menu.title": "タイトルへ",
		"options.title": "オプション",
		"options.resolution": "解像度",
		"options.language": "言語",
		"options.controls": "操作",
		"options.controls_mapping": "キーボード / コントローラー設定",
		"options.ui_only": "UIのみです。設定の適用はまだ実装されていません。",
		"options.changed": "項目を選択しました。設定の適用はまだ実装されていません。",
		"slot.new_game": "ニューゲーム",
		"slot.start_new_game": "ニューゲーム開始",
		"slot.load_game": "ロード",
		"slot.save": "セーブ",
		"slot.load": "ロード",
		"slot.confirm_overwrite": "上書きを確認",
		"slot.overwrite_prompt": "もう一度押すとスロット%dを上書きします。",
		"slot.overwrite_warning": "既存のセーブデータを上書きします。",
		"slot.empty": "スロット%d - 空",
		"slot.summary": "スロット%d - %s  %s",
		"slot.unknown": "不明",
		"slot.no_time": "時刻なし",
		"status.no_save_data": "セーブデータがありません",
		"status.saved_slot": "スロット%dにセーブしました",
		"status.loaded_slot": "スロット%dをロードしました",
		"status.save_failed": "セーブに失敗しました"
	},
	"zh_TW": {},
	"zh_CN": {},
	"ko": {},
	"fr": {},
	"de": {},
	"es": {}
}
